gglsbl/__init__.py
gglsbl/_version.py
gglsbl/client.py
gglsbl/protocol.py
gglsbl/storage.py
gglsbl/tests.py
gglsbl/utils.py
gglsbl-1.4.15.data/scripts/gglsbl_client.py
gglsbl-1.4.15.dist-info/LICENSE
gglsbl-1.4.15.dist-info/METADATA
gglsbl-1.4.15.dist-info/WHEEL
gglsbl-1.4.15.dist-info/top_level.txt
gglsbl-1.4.15.dist-info/RECORD
